pyacoustics_stc/__init__.py
pyacoustics_stc/constant.py
pyacoustics_stc/sound_tranmission_class.py
pyacoustics_stc/utils.py
pyacoustics_stc-0.4.0.dist-info/LICENSE
pyacoustics_stc-0.4.0.dist-info/WHEEL
pyacoustics_stc-0.4.0.dist-info/METADATA
pyacoustics_stc-0.4.0.dist-info/RECORD
