Metadata-Version: 2.1
Name: pyacoustics-stc
Version: 0.4.0
Summary: The Python library for Sound Transmission Class (STC) calculation
Home-page: https://github.com/bozzlab/pyacoustics-stc
License: MIT
Keywords: Acoustics,Sound Tranmission Class,Sound Transmission Loss,STC
Author: Peem Srinikorn (Bozzlab)
Author-email: peemsrinikorn@gmail.com
Requires-Python: >=3.8,<4.0
Classifier: License :: OSI Approved :: MIT License
Classifier: Programming Language :: Python :: 3
Classifier: Programming Language :: Python :: 3.8
Classifier: Programming Language :: Python :: 3.9
Requires-Dist: kaleido (==0.2.1)
Requires-Dist: pandas (>=1.4.3,<2.0.0)
Requires-Dist: plotly (>=5.9.0,<6.0.0)
Project-URL: Repository, https://github.com/bozzlab/pyacoustics-stc
